kedro_slurm-0.1.5.dist-info/METADATA
kedro_slurm-0.1.5.dist-info/WHEEL
kedro_slurm-0.1.5.dist-info/entry_points.txt
kedro_slurm-0.1.5.dist-info/licenses/LICENSE
kedro_slurm/__init__.py
kedro_slurm/pipeline/__init__.py
kedro_slurm/pipeline/node.py
kedro_slurm/runner/__init__.py
kedro_slurm/runner/slurm_runner.py
kedro_slurm/slurm.py
kedro_slurm-0.1.5.dist-info/RECORD
