Metadata-Version: 2.1
Name: kedro-slurm
Version: 0.1.5
Summary: Tools and runners for deploying and executing Kedro projects on SLURM
Author-Email: Francisco Piedrahita Velez <fpiedrah@brown.edu>
License: 0
Requires-Python: >=3.12
Requires-Dist: kedro>=0.19.10
